LICENSE
MANIFEST.in
README.md
quicktest.py
settings_test.py
setup.py
django_vkontakte_places.egg-info/PKG-INFO
django_vkontakte_places.egg-info/SOURCES.txt
django_vkontakte_places.egg-info/dependency_links.txt
django_vkontakte_places.egg-info/not-zip-safe
django_vkontakte_places.egg-info/requires.txt
django_vkontakte_places.egg-info/top_level.txt
vkontakte_places/__init__.py
vkontakte_places/__init__.pyc
vkontakte_places/factories.py
vkontakte_places/factories.pyc
vkontakte_places/lookups.py
vkontakte_places/lookups.pyc
vkontakte_places/models.py
vkontakte_places/models.pyc
vkontakte_places/tests.py
vkontakte_places/tests.pyc
vkontakte_places/management/__init__.py
vkontakte_places/management/__init__.pyc
vkontakte_places/management/commands/__init__.py
vkontakte_places/management/commands/fetch_vkontakte_countries.py