Metadata-Version: 1.1
Name: django-vkontakte-places
Version: 0.7.1
Summary: Django implementation for vkontakte API Places (any kind of geo objects)
Home-page: https://github.com/ramusus/django-vkontakte-places
Author: ramusus
Author-email: ramusus@gmail.com
License: BSD
Download-URL: http://pypi.python.org/pypi/django-vkontakte-places
Platform: UNKNOWN
Classifier: Development Status :: 4 - Beta
Classifier: Environment :: Web Environment
Classifier: Intended Audience :: Developers
Classifier: License :: OSI Approved :: BSD License
Classifier: Operating System :: OS Independent
Classifier: Programming Language :: Python
Classifier: Topic :: Software Development :: Libraries :: Python Modules
